highlighter/__init__.py
highlighter/__main__.py
highlighter/analysis.py
auto_highlighter-0.0.1.dist-info/entry_points.txt
auto_highlighter-0.0.1.dist-info/METADATA
auto_highlighter-0.0.1.dist-info/WHEEL
auto_highlighter-0.0.1.dist-info/RECORD
