Metadata-Version: 2.1
Name: auto-highlighter
Version: 0.0.1
Summary: automatically generate clips from VODs!
Author: porplax
Author-email: saynemarsh9@gmail.com
Requires-Python: >=3.11,<4.0
Classifier: Programming Language :: Python :: 3
Classifier: Programming Language :: Python :: 3.11
Classifier: Programming Language :: Python :: 3.12
Requires-Dist: numpy (>=2.1.1,<3.0.0)
Requires-Dist: opencv-python (>=4.10.0.84,<5.0.0.0)
Requires-Dist: pillow (>=10.4.0,<11.0.0)
Requires-Dist: pycparser (>=2.22,<3.0)
Requires-Dist: typer (>=0.12.5,<0.13.0)
